LICENCE.txt
README.md
setup.py
sabas_cals_dev/__init__.py
sabas_simple_calculator.egg-info/PKG-INFO
sabas_simple_calculator.egg-info/SOURCES.txt
sabas_simple_calculator.egg-info/dependency_links.txt
sabas_simple_calculator.egg-info/top_level.txt