Metadata-Version: 2.1
Name: sabas-simple-calculator
Version: 0.0.1
Summary: simple calculator
Home-page: UNKNOWN
Author: saba
Author-email: s.dvali@outlook.com
License: UNKNOWN
Platform: UNKNOWN
License-File: LICENCE.txt
